<?xml version="1.0" encoding="UTF-8"?>
<!DOCTYPE suite SYSTEM "https://testng.org/testng-1.0.dtd">
<suite name="Suite">
  <test thread-count="5" name="Test">
    <classes>
      <class name="TestNGImplimentation.CreateEventTest"/>
      <class name="TestNGImplimentation.CreateOrgWithTypeAndIndustryTest"/>
      <class name="TestNGImplimentation.CreateContactWithExistingOrgTest"/>
      <class name="TestNGImplimentation.CreateOrganizationTest"/>
      <class name="TestNGImplimentation.CreateAndDuplicateLeadTest"/>
    </classes>
  </test> <!-- Test -->
</suite> <!-- Suite -->
